<?xml version="1.0"?>
<registry>
  <record interface="plone.app.deco.interfaces.IDecoSettings" field="app_tiles">
    <value purge="False">
      <element>plone.app.standardtiles.image|media|Image|false|true|false|false|blur|tile-align-block|tile-align-right|tile-align-left</element>
      <element>plone.app.standardtiles.attachment|media|Attachment|false|true|false|false|blur|tile-align-block|tile-align-right|tile-align-left</element>
      <element>plone.app.standardtiles.video|media|Video|false|true|false|false|blur|tile-align-block|tile-align-right|tile-align-left</element>
      <element>plone.app.standardtiles.proxy|media|Proxy|false|true|false|false|blur|tile-align-block|tile-align-right|tile-align-left</element>
      <element>plone.app.standardtiles.navigation|media|Navtree|false|true|false|false|blur|tile-align-block|tile-align-right|tile-align-left</element>
      <element>plone.app.standardtiles.discussion|media|Discussion|false|true|false|false|blur|tile-align-block|tile-align-right|tile-align-left</element>
      <element>plone.app.standardtiles.content_listing|structure|Content listing|false|true|false|false|blur|tile-align-block|tile-align-right|tile-align-left</element>
      <element>plone.app.standardtiles.rss|media|RSS|false|true|false|false|blur|tile-align-block|tile-align-right|tile-align-left</element>
      <element>plone.app.standardtiles.tableofcontents|structure|Table of contents|false|true|false|false|blur|tile-align-block|tile-align-right|tile-align-left</element>
      <element>plone.app.standardtiles.document_byline|structure|Document byline|false|true|false|false|blur|tile-align-block|tile-align-right|tile-align-left</element>
      <element>plone.app.standardtiles.related_items|structure|Related items|false|true|false|false|blur|tile-align-block|tile-align-right|tile-align-left</element>
      <element>plone.app.standardtiles.calendar|media|Calendar|false|true|false|false|blur|tile-align-block|tile-align-right|tile-align-left</element>
    </value>
  </record>

  <record interface="plone.app.standardtiles.interfaces.IStandardTilesSettings" field="images_repo_path">
    <value>images</value>
  </record>
</registry>
